ollama_bar/__main__.py
ollama_bar/_version.py
ollama_bar/command_display_window.py
ollama_bar/ollama_bar_app.py
ollama_bar/output_capture.py
ollama_bar/process_monitor.py
ollama_bar/webui.py
ollama_bar/resources/off.svg
ollama_bar/resources/ollama.png
ollama_bar/resources/on.svg
ollama_bar-0.2.0.dist-info/LICENSE
ollama_bar-0.2.0.dist-info/METADATA
ollama_bar-0.2.0.dist-info/WHEEL
ollama_bar-0.2.0.dist-info/entry_points.txt
ollama_bar-0.2.0.dist-info/top_level.txt
ollama_bar-0.2.0.dist-info/RECORD
