Metadata-Version: 2.1
Name: ollama-bar
Version: 0.2.0
Summary: Macos status bar app that allows you to start/stop/view ollama from the menu bar.
License: Apache-2.0
Project-URL: Source, https://github.com/IBM/ollama-bar
Classifier: License :: OSI Approved :: Apache Software License
Requires-Python: >=3.11
License-File: LICENSE
Requires-Dist: rumps <0.5.0,>=0.4.0
Requires-Dist: open-webui <0.4,>=0.3.10
Provides-Extra: dev
Requires-Dist: ollama-bar[dev-build,dev-fmt,dev-test] ; extra == 'dev'
Provides-Extra: dev-build
Requires-Dist: setuptools >=60 ; extra == 'dev-build'
Requires-Dist: setuptools-scm >=8.0 ; extra == 'dev-build'
Requires-Dist: briefcase <0.4,>=0.3.19 ; extra == 'dev-build'
Provides-Extra: dev-fmt
Requires-Dist: pre-commit <4.0,>=3.0.4 ; extra == 'dev-fmt'
Requires-Dist: ruff ==0.4.10 ; extra == 'dev-fmt'
Provides-Extra: dev-test
Requires-Dist: pytest >=6 ; extra == 'dev-test'
Requires-Dist: pytest-cov >=2.10.1 ; extra == 'dev-test'
Requires-Dist: pytest-timeout <3,>=2.1.0 ; extra == 'dev-test'
Requires-Dist: tls-test-tools <0.2,>=0.1.1 ; extra == 'dev-test'
Requires-Dist: requests <3,>=2.32.2 ; extra == 'dev-test'
